{"GeneratedCodeFiles":[],"GeneratedXamlFiles":["C:\\Users\\wejdj\\OneDrive\\Desktop\\Trace Application\\PCBTracker.UI\\obj\\Debug\\net9.0-windows10.0.19041.0\\win10-x64\\Platforms\\Windows\\App.xaml"],"GeneratedXbfFiles":["C:\\Users\\wejdj\\OneDrive\\Desktop\\Trace Application\\PCBTracker.UI\\obj\\Debug\\net9.0-windows10.0.19041.0\\win10-x64\\Platforms\\Windows\\App.xbf"],"GeneratedXamlPagesFiles":[],"MSBuildLogEntries":[{"SubCategory":null,"ErrorCode":null,"HelpKeyword":null,"File":null,"LineNumber":0,"ColumnNumber":0,"EndLineNumber":0,"EndColumnNumber":0,"Message":"Xaml Compiler Marker: 8:53:55 AM:  84 perfXC_StartPass2, PCBTracker.UI"},{"SubCategory":null,"ErrorCode":null,"HelpKeyword":null,"File":null,"LineNumber":0,"ColumnNumber":0,"EndLineNumber":0,"EndColumnNumber":0,"Message":"Xaml Compiler Marker: 8:53:55 AM: 109 perfXC_FingerprintCheck, Using managed HashForWinMD"},{"SubCategory":null,"ErrorCode":null,"HelpKeyword":null,"File":null,"LineNumber":0,"ColumnNumber":0,"EndLineNumber":0,"EndColumnNumber":0,"Message":"Xaml Compiler Marker: 8:53:55 AM: 347 perfXC_FingerprintCheck, Using managed HashForWinMD"},{"SubCategory":null,"ErrorCode":null,"HelpKeyword":null,"File":null,"LineNumber":0,"ColumnNumber":0,"EndLineNumber":0,"EndColumnNumber":0,"Message":"Xaml Compiler Marker: 8:53:55 AM: 370 perfXC_FingerprintCheck, Using managed HashForWinMD"},{"SubCategory":null,"ErrorCode":null,"HelpKeyword":null,"File":null,"LineNumber":0,"ColumnNumber":0,"EndLineNumber":0,"EndColumnNumber":0,"Message":"Xaml Compiler Marker: 8:53:55 AM: 392 perfXC_RestoredGeneratedPass2CodeFileBackup"},{"SubCategory":null,"ErrorCode":null,"HelpKeyword":null,"File":null,"LineNumber":0,"ColumnNumber":0,"EndLineNumber":0,"EndColumnNumber":0,"Message":"Xaml Compiler Marker: 8:53:55 AM: 404 perfXC_RestoredTypeInfoBackup"}]}